azure/mgmt/healthdataaiservices/__init__.py
azure/mgmt/healthdataaiservices/_client.py
azure/mgmt/healthdataaiservices/_configuration.py
azure/mgmt/healthdataaiservices/_model_base.py
azure/mgmt/healthdataaiservices/_patch.py
azure/mgmt/healthdataaiservices/_serialization.py
azure/mgmt/healthdataaiservices/_version.py
azure/mgmt/healthdataaiservices/py.typed
azure/mgmt/healthdataaiservices/aio/__init__.py
azure/mgmt/healthdataaiservices/aio/_client.py
azure/mgmt/healthdataaiservices/aio/_configuration.py
azure/mgmt/healthdataaiservices/aio/_patch.py
azure/mgmt/healthdataaiservices/aio/operations/__init__.py
azure/mgmt/healthdataaiservices/aio/operations/_operations.py
azure/mgmt/healthdataaiservices/aio/operations/_patch.py
azure/mgmt/healthdataaiservices/models/__init__.py
azure/mgmt/healthdataaiservices/models/_enums.py
azure/mgmt/healthdataaiservices/models/_models.py
azure/mgmt/healthdataaiservices/models/_patch.py
azure/mgmt/healthdataaiservices/operations/__init__.py
azure/mgmt/healthdataaiservices/operations/_operations.py
azure/mgmt/healthdataaiservices/operations/_patch.py
azure_mgmt_healthdataaiservices-1.0.0.dist-info/LICENSE
azure_mgmt_healthdataaiservices-1.0.0.dist-info/METADATA
azure_mgmt_healthdataaiservices-1.0.0.dist-info/WHEEL
azure_mgmt_healthdataaiservices-1.0.0.dist-info/top_level.txt
azure_mgmt_healthdataaiservices-1.0.0.dist-info/RECORD
